{
    "0":[
        [
            -23.56291237745968,
            -46.646993657582655,
            "300000000001",
            "0"
        ]
    ],
    "1":[
        [
            -23.565272197150616,
            -46.64586832736136,
            "300000000002",
            "3"
        ]
    ],
    "10":[
        [
            -23.565206338855333,
            -46.64636589850852,
            "300000000011",
            "3"
        ]
    ],
    "11":[
        [
            -23.56547562138923,
            -46.64766852429334,
            "300000000012",
            "4"
        ]
    ],
    "12":[
        [
            -23.56498444410369,
            -46.647286981142095,
            "300000000013",
            "4"
        ]
    ],
    "13":[
        [
            -23.559341364185435,
            -46.649374396900065,
            "300000000014",
            "1"
        ]
    ],
    "14":[
        [
            -23.56444696592188,
            -46.6490950753251,
            "300000000015",
            "5"
        ]
    ],
    "15":[
        [
            -23.56433993719927,
            -46.65011760895175,
            "300000000016",
            "2"
        ]
    ],
    "16":[
        [
            -23.566456545571835,
            -46.646951705101465,
            "8565699864",
            "1"
        ]
    ],
    "17":[
        [
            -23.560708599490965,
            -46.64874362903618,
            "300000000018",
            "0"
        ]
    ],
    "2":[
        [
            -23.563442822177244,
            -46.651593132511294,
            "300000000003",
            "1"
        ]
    ],
    "3":[
        [
            -23.56506269570793,
            -46.646729607047014,
            "300000000004",
            "4"
        ]
    ],
    "4":[
        [
            -23.56394772902268,
            -46.64791376097326,
            "300000000005",
            "3"
        ]
    ],
    "5":[
        [
            -23.56467263161901,
            -46.649394166616325,
            "300000000006",
            "0"
        ]
    ],
    "6":[
        [
            -23.562986404807695,
            -46.64700623230718,
            "300000000007",
            "3"
        ]
    ],
    "7":[
        [
            -23.562784432210222,
            -46.64736857804934,
            "300000000008",
            "4"
        ]
    ],
    "8":[
        [
            -23.563059589563125,
            -46.65159667860801,
            "300000000009",
            "1"
        ]
    ],
    "9":[
        [
            -23.565610378598493,
            -46.64909012569154,
            "300000000010",
            "0"
        ]
    ],
    "total_length":3272.0682989230872,
    "total_time":3.2741241455078125
}