{
    "0":[
        [
            -19.918204437644054,
            -43.94814434807299,
            "300000000001",
            "0"
        ]
    ],
    "1":[
        [
            -19.91954924794005,
            -43.94385858051208,
            "300000000002",
            "3"
        ]
    ],
    "10":[
        [
            -19.91877969765998,
            -43.94143513796526,
            "300000000011",
            "3"
        ]
    ],
    "11":[
        [
            -19.92422128063375,
            -43.94421013049516,
            "300000000012",
            "4"
        ]
    ],
    "12":[
        [
            -19.919638329664267,
            -43.944505405590405,
            "300000000013",
            "4"
        ]
    ],
    "13":[
        [
            -19.922631374129693,
            -43.943474865349245,
            "300000000014",
            "1"
        ]
    ],
    "14":[
        [
            -19.921560696530662,
            -43.941554490290734,
            "300000000015",
            "5"
        ]
    ],
    "15":[
        [
            -19.917885390918663,
            -43.94168152015633,
            "300000000016",
            "2"
        ]
    ],
    "16":[
        [
            -19.915622161490695,
            -43.94359171771138,
            "300000000017",
            "1"
        ]
    ],
    "17":[
        [
            -19.921032801112254,
            -43.945838653947554,
            "300000000018",
            "3"
        ]
    ],
    "18":[
        [
            -19.918012977124768,
            -43.94185319392479,
            "300000000019",
            "4"
        ]
    ],
    "19":[
        [
            -19.921268806486605,
            -43.944008207829704,
            "8979076650",
            "4"
        ]
    ],
    "2":[
        [
            -19.919326020765382,
            -43.93981172286755,
            "8978967862",
            "1"
        ]
    ],
    "20":[
        [
            -19.921451181193802,
            -43.94123958553074,
            "300000000021",
            "5"
        ]
    ],
    "21":[
        [
            -19.922153329903832,
            -43.94475247948841,
            "300000000022",
            "0"
        ]
    ],
    "22":[
        [
            -19.92000532490748,
            -43.94033261490146,
            "300000000023",
            "3"
        ]
    ],
    "23":[
        [
            -19.918114412018614,
            -43.94344269133487,
            "300000000024",
            "0"
        ]
    ],
    "3":[
        [
            -19.919587965757483,
            -43.94296843167679,
            "300000000004",
            "4"
        ]
    ],
    "4":[
        [
            -19.920786913396668,
            -43.946036388171905,
            "300000000005",
            "3"
        ]
    ],
    "5":[
        [
            -19.920193240323044,
            -43.94529728845468,
            "300000000006",
            "0"
        ]
    ],
    "6":[
        [
            -19.919293520755893,
            -43.94599414069144,
            "300000000007",
            "3"
        ]
    ],
    "7":[
        [
            -19.9191017664793,
            -43.94554813883897,
            "300000000008",
            "4"
        ]
    ],
    "8":[
        [
            -19.92111973499766,
            -43.94213818878983,
            "300000000009",
            "1"
        ]
    ],
    "9":[
        [
            -19.917569125976026,
            -43.945479473269025,
            "300000000010",
            "0"
        ]
    ],
    "total_length":6476.674631109359,
    "total_time":9.01160478591919
}