{
    "0":[
        [
            -19.921136952396157,
            -43.94430503589559,
            "300000000001",
            "0"
        ]
    ],
    "1":[
        [
            -19.919783357069385,
            -43.94529713861198,
            "300000000002",
            "3"
        ]
    ],
    "10":[
        [
            -19.924279639176774,
            -43.94203309586815,
            "300000000011",
            "3"
        ]
    ],
    "11":[
        [
            -19.919631256100192,
            -43.94130035821297,
            "300000000012",
            "4"
        ]
    ],
    "12":[
        [
            -19.921835495181725,
            -43.94133560107804,
            "300000000013",
            "4"
        ]
    ],
    "13":[
        [
            -19.919440227931744,
            -43.94340515097543,
            "300000000014",
            "1"
        ]
    ],
    "14":[
        [
            -19.91459601151055,
            -43.94705833865067,
            "300000000015",
            "5"
        ]
    ],
    "15":[
        [
            -19.920230475031357,
            -43.94172139767203,
            "300000000016",
            "2"
        ]
    ],
    "16":[
        [
            -19.922266706104203,
            -43.943803677874975,
            "300000000017",
            "1"
        ]
    ],
    "17":[
        [
            -19.92343886888937,
            -43.94408902940042,
            "300000000018",
            "3"
        ]
    ],
    "18":[
        [
            -19.920567933123078,
            -43.943816820105404,
            "300000000019",
            "4"
        ]
    ],
    "19":[
        [
            -19.917578041117853,
            -43.942976412665985,
            "300000000020",
            "4"
        ]
    ],
    "2":[
        [
            -19.91922877722549,
            -43.941708569171944,
            "300000000003",
            "1"
        ]
    ],
    "20":[
        [
            -19.920405759219204,
            -43.942173995794285,
            "300000000021",
            "5"
        ]
    ],
    "21":[
        [
            -19.91978925999705,
            -43.94076423714771,
            "300000000022",
            "0"
        ]
    ],
    "22":[
        [
            -19.916875955366276,
            -43.942311550257735,
            "300000000023",
            "3"
        ]
    ],
    "23":[
        [
            -19.920629742523715,
            -43.94202899770459,
            "300000000024",
            "0"
        ]
    ],
    "3":[
        [
            -19.92079942843133,
            -43.946232159093704,
            "300000000004",
            "4"
        ]
    ],
    "4":[
        [
            -19.919785439028683,
            -43.94184889521733,
            "300000000005",
            "3"
        ]
    ],
    "5":[
        [
            -19.920891144919967,
            -43.94006849097421,
            "300000000006",
            "0"
        ]
    ],
    "6":[
        [
            -19.923868777115928,
            -43.94485660148179,
            "300000000007",
            "3"
        ]
    ],
    "7":[
        [
            -19.922274881406707,
            -43.94462714560778,
            "300000000008",
            "4"
        ]
    ],
    "8":[
        [
            -19.92127481348533,
            -43.94305208753705,
            "300000000009",
            "1"
        ]
    ],
    "9":[
        [
            -19.922205940103503,
            -43.9446921714556,
            "300000000010",
            "0"
        ]
    ],
    "total_length":5983.930602681455,
    "total_time":1.9605836868286133
}